abeluna/__init__.py
abeluna/main.py
abeluna/settings.py
abeluna/util.py
abeluna/sync/__init__.py
abeluna/sync/calendar.py
abeluna/sync/local.py
abeluna/sync/server.py
abeluna/ui/menubar.ui
abeluna/widgets/__init__.py
abeluna/widgets/datetime_picker.py
abeluna/widgets/dropdown_select.py
abeluna/widgets/error_dialog.py
abeluna/windows/__init__.py
abeluna/windows/settings.py
abeluna/windows/todolist.py
abeluna-1.1.3.dist-info/LICENSE
abeluna-1.1.3.dist-info/METADATA
abeluna-1.1.3.dist-info/WHEEL
abeluna-1.1.3.dist-info/entry_points.txt
abeluna-1.1.3.dist-info/top_level.txt
abeluna-1.1.3.dist-info/RECORD
