Metadata-Version: 2.1
Name: abeluna
Version: 1.1.3
Summary: A simple GUI to-do/task manager with CalDAV support.
Home-page: https://github.com/Ninjaclasher/abeluna
Author: Evan Zhang
Classifier: Development Status :: 4 - Beta
Classifier: Environment :: X11 Applications :: GTK
Classifier: Intended Audience :: End Users/Desktop
Classifier: License :: OSI Approved :: GNU Affero General Public License v3 or later (AGPLv3+)
Classifier: Operating System :: POSIX :: Linux
Classifier: Programming Language :: Python
Classifier: Programming Language :: Python :: 3.7
Classifier: Programming Language :: Python :: 3.8
Classifier: Programming Language :: Python :: 3.9
Classifier: Programming Language :: Python :: 3.10
License-File: LICENSE
Requires-Dist: pygobject
Requires-Dist: humanize
Requires-Dist: icalendar
Requires-Dist: caldav
